printtt_test/printtt_test.py
printtt_test-0.0.2.dist-info/DESCRIPTION.rst
printtt_test-0.0.2.dist-info/METADATA
printtt_test-0.0.2.dist-info/RECORD
printtt_test-0.0.2.dist-info/WHEEL
printtt_test-0.0.2.dist-info/metadata.json
printtt_test-0.0.2.dist-info/top_level.txt
