Metadata-Version: 2.0
Name: printtt-test
Version: 0.0.2
Summary: testing printtt_test
Home-page: https://github.com/pajuhy123/printtt_test
Author: someone
Author-email: UNKNOWN
License: UNKNOWN
Download-URL: https://github.com/pajuhy123/printtt_test.git
Keywords: print
Platform: UNKNOWN
